{"dependencies":[{"name":"inherits","loc":{"line":3,"column":25}},{"name":"./der","loc":{"line":5,"column":27}}],"generated":{"js":"'use strict';\n\nconst inherits = require('inherits');\n\nconst DEREncoder = require('./der');\n\nfunction PEMEncoder(entity) {\n  DEREncoder.call(this, entity);\n  this.enc = 'pem';\n}\ninherits(PEMEncoder, DEREncoder);\nmodule.exports = PEMEncoder;\n\nPEMEncoder.prototype.encode = function encode(data, options) {\n  const buf = DEREncoder.prototype.encode.call(this, data);\n\n  const p = buf.toString('base64');\n  const out = [ '-----BEGIN ' + options.label + '-----' ];\n  for (let i = 0; i < p.length; i += 64)\n    out.push(p.slice(i, i + 64));\n  out.push('-----END ' + options.label + '-----');\n  return out.join('\\n');\n};\n"},"hash":"383a1d76c9b3b44b646422857d0ddbe0"}