{"dependencies":[{"name":"./util/assertString","loc":{"line":8,"column":51}}],"generated":{"js":"\"use strict\";\n\nObject.defineProperty(exports, \"__esModule\", {\n  value: true\n});\nexports.default = toInt;\n\nvar _assertString = _interopRequireDefault(require(\"./util/assertString\"));\n\nfunction _interopRequireDefault(obj) { return obj && obj.__esModule ? obj : { default: obj }; }\n\nfunction toInt(str, radix) {\n  (0, _assertString.default)(str);\n  return parseInt(str, radix || 10);\n}\n\nmodule.exports = exports.default;\nmodule.exports.default = exports.default;"},"hash":"be2703c892b9aa22a9e782180b027ca4"}