{"dependencies":[],"generated":{"js":"\"use strict\";\n\nObject.defineProperty(exports, \"__esModule\", {\n  value: true\n});\nexports.default = toString;\n\nfunction _typeof(obj) { \"@babel/helpers - typeof\"; if (typeof Symbol === \"function\" && typeof Symbol.iterator === \"symbol\") { _typeof = function _typeof(obj) { return typeof obj; }; } else { _typeof = function _typeof(obj) { return obj && typeof Symbol === \"function\" && obj.constructor === Symbol && obj !== Symbol.prototype ? \"symbol\" : typeof obj; }; } return _typeof(obj); }\n\nfunction toString(input) {\n  if (_typeof(input) === 'object' && input !== null) {\n    if (typeof input.toString === 'function') {\n      input = input.toString();\n    } else {\n      input = '[object Object]';\n    }\n  } else if (input === null || typeof input === 'undefined' || isNaN(input) && !input.length) {\n    input = '';\n  }\n\n  return String(input);\n}\n\nmodule.exports = exports.default;\nmodule.exports.default = exports.default;"},"hash":"092e1b6b4ccb5e064811bf21fa24c5ad"}